LogicGates/ANDGate/3InputGate/ANDGate_3Input_BehavioralCode.v
module ANDGate_3Input_Behavioral (y, a, b, c);

	output reg y;
	input a, b, c;

	always @ (*) begin
	if (a == 1 && b == 1 && c == 1)
		y = 1;
	else
		y = 0;
	end

endmodule

LogicGates/ANDGate/3InputGate/ANDGate_3Input_WithAlwaysBlock.v
module ANDGate_3Input_WithAlwaysBlock (y, a, b, c);

	output reg y;
	input a, b, c;

	always @ (*) begin
		y = (a & b & c);
	end

endmodule

LogicGates/ANDGate/3InputGate/ANDGate_3Input_DataflowCode.v
module ANDGate_3Input_Dataflow (y, a, b, c);

	output y;
	input a, b, c;

	assign y = (a & b & c);

endmodule

LogicGates/ANDGate/3InputGate/ANDGate_3Input_StructuralCode.v
module ANDGate_3Input_Structural (y, a, b, c);

	output y;
	input a, b, c;

	and (y, a, b, c);

endmodule

LogicGates/ANDGate/3InputGate/ANDGate_3Input_Testbench.v
module ANDGate_3Input_Testbench;

	wire y_structural, y_dataflow, y_withAlwaysBlock, y_behavioral;
	reg a, b, c;

	ANDGate_3Input_Structural uut1 (.y(y_structural), .a(a), .b(b), .c(c));
	ANDGate_3Input_Dataflow uut2 (.y(y_dataflow), .a(a), .b(b), .c(c));
	ANDGate_3Input_WithAlwaysBlock uut3 (.y(y_withAlwaysBlock), .a(a), .b(b), .c(c));
	ANDGate_3Input_Behavioral uut4 (.y(y_behavioral), .a(a), .b(b), .c(c));

	initial begin
	

	$dumpfile ("ANDGate_3Input_Simulation.vcd");
	$dumpvars (0, ANDGate_3Input_Testbench);

	a = 0; b = 0; c = 0;
	#10 a = 0; b = 0; c = 1;
	#10 a = 0; b = 1; c = 0;
	#10 a = 0; b = 1; c = 1;
	#10 a = 1; b = 0; c = 0;
	#10 a = 1; b = 0; c = 1;
	#10 a = 1; b = 1; c = 0;
	#10 a = 1; b = 1; c = 1;
	#10 $finish;

	end

endmodule

LogicGates/ANDGate/3InputGate/ANDGate_3Input_Simulation.vcd
$date
	Wed Jun  3 09:30:07 2026
$end
$version
	Icarus Verilog
$end
$timescale
	1s
$end
$scope module ANDGate_3Input_Testbench $end
$var wire 1 ! y_withAlwaysBlock $end
$var wire 1 " y_structural $end
$var wire 1 # y_dataflow $end
$var wire 1 $ y_behavioral $end
$var reg 1 % a $end
$var reg 1 & b $end
$var reg 1 ' c $end
$scope module uut1 $end
$var wire 1 % a $end
$var wire 1 & b $end
$var wire 1 ' c $end
$var wire 1 " y $end
$upscope $end
$scope module uut2 $end
$var wire 1 % a $end
$var wire 1 & b $end
$var wire 1 ' c $end
$var wire 1 # y $end
$upscope $end
$scope module uut3 $end
$var wire 1 % a $end
$var wire 1 & b $end
$var wire 1 ' c $end
$var reg 1 ! y $end
$upscope $end
$scope module uut4 $end
$var wire 1 % a $end
$var wire 1 & b $end
$var wire 1 ' c $end
$var reg 1 $ y $end
$upscope $end
$upscope $end
$enddefinitions $end
$comment Show the parameter values. $end
$dumpall
$end
#0
$dumpvars
0'
0&
0%
0$
0#
0"
0!
$end
#10
1'
#20
0'
1&
#30
1'
#40
0'
0&
1%
#50
1'
#60
0'
1&
#70
1"
1#
1!
1$
1'
